sfast/_C.cpython-310-x86_64-linux-gnu.so
sfast/__init__.py
sfast/compilers/__init__.py
sfast/compilers/diffusion_pipeline_compiler.py
sfast/compilers/stable_diffusion_pipeline_compiler.py
sfast/cuda/__init__.py
sfast/cuda/graphs.py
sfast/dynamo/__init__.py
sfast/dynamo/backends/__init__.py
sfast/dynamo/backends/registry.py
sfast/dynamo/backends/sfast_jit.py
sfast/hooks/__init__.py
sfast/hooks/module_jit_hook.py
sfast/jit/__init__.py
sfast/jit/overrides.py
sfast/jit/trace_helper.py
sfast/jit/utils.py
sfast/jit/passes/__init__.py
sfast/jit/passes/triton_passes.py
sfast/libs/__init__.py
sfast/libs/diffusers/__init__.py
sfast/libs/diffusers/image_processor.py
sfast/libs/diffusers/xformers_attention.py
sfast/libs/xformers/__init__.py
sfast/libs/xformers/xformers_attention.py
sfast/profile/__init__.py
sfast/profile/auto_profiler.py
sfast/profile/cprofile.py
sfast/profile/pretty_profile.py
sfast/triton/__init__.py
sfast/triton/torch_ops.py
sfast/triton/modules/__init__.py
sfast/triton/modules/diffusers.py
sfast/triton/modules/native.py
sfast/triton/modules/patch.py
sfast/triton/ops/__init__.py
sfast/triton/ops/activation.py
sfast/triton/ops/conv.py
sfast/triton/ops/copy.py
sfast/triton/ops/group_norm.py
sfast/triton/ops/layer_norm.py
sfast/triton/ops/utils.py
sfast/utils/__init__.py
sfast/utils/aot_printer.py
sfast/utils/compute_precision.py
sfast/utils/copy.py
sfast/utils/copy_func.py
sfast/utils/custom_python_operator.py
sfast/utils/env.py
sfast/utils/flat_tensors.py
sfast/utils/gpu_device.py
sfast/utils/memory_format.py
sfast/utils/patch.py
sfast/utils/torch_dispatch.py
sfast/utils/term_image/__init__.py
sfast/utils/term_image/climage.py
sfast/utils/term_image/image_to_ansi.py
sfast/utils/term_image/imgcat.py
sfast/utils/term_image/kdtree.py
stable_fast_pruna-1.0.8.dist-info/LICENSE
stable_fast_pruna-1.0.8.dist-info/METADATA
stable_fast_pruna-1.0.8.dist-info/WHEEL
stable_fast_pruna-1.0.8.dist-info/top_level.txt
stable_fast_pruna-1.0.8.dist-info/RECORD
