Metadata-Version: 2.1
Name: stable-fast-pruna
Version: 1.0.8
Summary: Stable Fast is an ultra lightweight performance optimization framework for Hugging Fase diffuser pipelines.
Home-page: https://github.com/chengzeyi/stable-fast
Author: Cheng Zeyi
License: UNKNOWN
Platform: UNKNOWN
Requires-Python: >=3.7
License-File: LICENSE
Requires-Dist: torch<2.10,>=2.9
Provides-Extra: all
Provides-Extra: dev
Requires-Dist: Pillow; extra == "dev"
Requires-Dist: numpy; extra == "dev"
Requires-Dist: opencv-python; extra == "dev"
Requires-Dist: prettytable; extra == "dev"
Requires-Dist: pytest; extra == "dev"
Provides-Extra: diffusers
Requires-Dist: diffusers>=0.19.0; extra == "diffusers"
Requires-Dist: transformers; extra == "diffusers"
Provides-Extra: triton
Requires-Dist: triton>=2.1.0; extra == "triton"
Provides-Extra: xformers
Requires-Dist: xformers>=0.0.20; extra == "xformers"
